solomon/__init__.py
solomon/base/ViewController.swift
solomon/tmpl/Contract.tmpl
solomon/tmpl/Model.tmpl
solomon/tmpl/Presenter.tmpl
solomon/tmpl/UIViewController.tmpl
solomon-0.0.4.dist-info/LICENSE
solomon-0.0.4.dist-info/METADATA
solomon-0.0.4.dist-info/WHEEL
solomon-0.0.4.dist-info/entry_points.txt
solomon-0.0.4.dist-info/top_level.txt
solomon-0.0.4.dist-info/RECORD
