Metadata-Version: 2.1
Name: solomon
Version: 0.0.4
Summary: Solomon tools
Home-page: https://github.com/ztimc/solomon
Author: ztimc
Author-email: ztimcz@gmail.com
License: The MIT License (MIT)
Requires-Dist: pbxproj (>=2.6.0)
